{
  "type_description_msg": {
    "type_description": {
      "type_name": "ros2_grasping/action/Attacher_Result",
      "fields": [
        {
          "name": "result",
          "type": {
            "type_id": 17,
            "capacity": 0,
            "string_capacity": 0,
            "nested_type_name": ""
          },
          "default_value": ""
        }
      ]
    },
    "referenced_type_descriptions": []
  },
  "type_hashes": [
    {
      "type_name": "ros2_grasping/action/Attacher_Result",
      "hash_string": "RIHS01_55699eefff2fd13cd016f9dec1efd6821e0c6a57ef64bd970da3266b08a7a489"
    }
  ]
}